{
  "schema_version": "1.0.0",
  "rule_set": "content_types",
  "description": "小红书/Rednote 种草内容类型分类规则，用于判断单篇笔记在品牌营销链路中的主要角色。",
  "categories": [
    {
      "key": "brand_awareness",
      "label": "品牌认知型",
      "signals": ["品牌名高频出现", "品牌定位", "品牌背书", "品牌故事", "行业资质", "权威认证", "官方活动", "品牌优势"],
      "description": "内容主要目标是建立品牌可信度和基础认知，常用品牌定位、资质背书、团队背景、服务规模等信息，但如果缺少用户场景和真实体验，容易产生硬广感。",
      "example": "第一次了解 Brand A，原来它主打的是长期陪跑和系统化学习路径。"
    },
    {
      "key": "product_experience",
      "label": "产品体验型",
      "signals": ["上课体验", "使用感受", "界面截图", "课程流程", "老师互动", "服务反馈", "孩子反应", "体验记录"],
      "description": "内容围绕真实使用过程展开，重点描述产品功能、服务流程、体验细节和用户感受，适合补充信任，但需要进一步回答为什么值得选择。",
      "example": "试听后我重点看了老师互动、课后反馈和孩子愿不愿意继续上。"
    },
    {
      "key": "course_decision",
      "label": "选课决策型",
      "signals": ["怎么选", "选择标准", "选课逻辑", "适合谁", "不适合谁", "阶段匹配", "家长决策", "判断框架"],
      "description": "内容先解释用户该如何判断，再自然带出品牌或方案，是种草转化中最有决策影响力的内容类型，适合沉淀为核心选题模板。",
      "example": "给低龄孩子选课，我会先看开口频率、纠音反馈、课后练习和阶段目标。"
    },
    {
      "key": "review_comparison",
      "label": "测评对比型",
      "signals": ["对比", "测评", "横评", "哪家更适合", "优缺点", "表格", "三家", "体验下来"],
      "description": "内容通过多个品牌、产品或方案的横向比较帮助用户降低选择成本，重点应放在客观维度和适配人群，避免过度拉踩竞品。",
      "example": "试了几类线上课后，我把互动强度、反馈细度和价格透明度做了个对比表。"
    },
    {
      "key": "pitfall_guide",
      "label": "避坑攻略型",
      "signals": ["避坑", "别踩坑", "不建议", "注意", "坑点", "踩雷", "怎么买不亏", "清单"],
      "description": "内容通过提醒误区、试错成本和判断标准来建立作者专业感，适合承接高意向搜索，但表达要具体，不能只制造焦虑。",
      "example": "别只看单节课价格，真正要看课后反馈、练习闭环和孩子是否持续开口。"
    },
    {
      "key": "result_feedback",
      "label": "结果反馈型",
      "signals": ["变化", "提升", "反馈", "结果", "从不敢到敢", "坚持后", "前后对比", "阶段复盘"],
      "description": "内容以学习或使用后的变化作为核心证据，适合增强信任和收藏价值，但需要避免绝对化效果承诺。",
      "example": "坚持一段时间后，孩子从只会跟读变成能主动说完整句。"
    },
    {
      "key": "conversion_driven",
      "label": "成交转化型",
      "signals": ["试听", "领取", "私信", "评论区", "报名", "优惠", "限时", "资料包", "进群"],
      "description": "内容以引导咨询、试听、领资料、报名或进群为主要目标，适合放在转化链路后段；如果 CTA 过早或过重，会削弱原生种草感。",
      "example": "需要选课清单的家长，可以在评论区留言，我整理了适合不同阶段的判断表。"
    }
  ]
}
